Workbook
Name aporte: APP!$D$17
Name dividendo: APP!$D$21
Name patrimonio: APP!$D$20
Name qtd_anos: APP!$D$18
Name rendimento_carteira: APP!$D$13
Name salario: APP!$D$12
Name sugestao_investimento: APP!$D$14
Name taxa_mensal: APP!$D$19

Sheet APP
B11: CONFIGURAÇÕES
B12: Salário | D12: 5800
B13: Rendimento Cateira | D13: 0.006
B14: Sugestão de Investimento (30%) | D14: =salario*30% -> 1740
B16: INVESTIMENTO MENSAL
B17: Quanto investir por mês ? | D17: 800
B18: Por quantos anos ? | D18: 5
B19: Taxa de rendimento mensal ? | D19: 0.01079
B20: Patrimônio acumulado ? | D20: =FV(taxa_mensal,qtd_anos*12,aporte*-1) -> 67021.531
B21: Dividendos mensais ? | D21: =patrimonio*rendimento_carteira -> 402.12919
B23: Cenários | D23: Dividendo
A24: 2 | B24: Quanto em 2 anos ? | C24: =FV($D$19,$A24*12,$D$17*-1) -> 21782.102 | D24: =C24*rendimento_carteira -> 130.69261
A25: 5 | B25: Quanto em 5 anos ? | C25: =FV($D$19,$A25*12,$D$17*-1) -> 67021.531 | D25: =C25*rendimento_carteira -> 402.12919
A26: 10 | B26: Quanto em 10 anos ? | C26: =FV($D$19,$A26*12,$D$17*-1) -> 194627.37 | D26: =C26*rendimento_carteira -> 1167.7642
A27: 20 | B27: Quanto em 20 anos ? | C27: =FV($D$19,$A27*12,$D$17*-1) -> 900158.72 | D27: =C27*rendimento_carteira -> 5400.9523
A28: 30 | B28: Quanto em 30 anos ? | C28: =FV($D$19,$A28*12,$D$17*-1) -> 3457735.7 | D28: =C28*rendimento_carteira -> 20746.414
B32: PERFIL | C32: Agressivo
B33: VALOR A SER INVESTIDO POR MÊS | C33: =aporte -> 800
B35: TIPO DE FII | C35: Percentual Sugerido | D35: Valores
B36: PAPEL | C36: =VLOOKUP($C$32&"-"&B36,DATABASE!$C:$F,4,FALSE) -> 0.5 | D36: =C36*$C$33 -> 400
B37: TIJOLO | C37: =VLOOKUP($C$32&"-"&B37,DATABASE!$C:$F,4,FALSE) -> 0.1 | D37: =C37*$C$33 -> 80
B38: HÍBRIDOS | C38: =VLOOKUP($C$32&"-"&B38,DATABASE!$C:$F,4,FALSE) -> 0.05 | D38: =C38*$C$33 -> 40
B39: FOFs | C39: =VLOOKUP($C$32&"-"&B39,DATABASE!$C:$F,4,FALSE) -> 0.05 | D39: =C39*$C$33 -> 40
B40: DESENVOLVIMENTO | C40: =VLOOKUP($C$32&"-"&B40,DATABASE!$C:$F,4,FALSE) -> 0.2 | D40: =C40*$C$33 -> 160
B41: HOTELARIAS | C41: =VLOOKUP($C$32&"-"&B41,DATABASE!$C:$F,4,FALSE) -> 0.1 | D41: =C41*$C$33 -> 80
D42: =SUM(D36:D41) -> 800

Sheet DATABASE
C2: CHAVE | D2: PERFIL | E2: TIPO DE FII | F2: % | H2: Moderado-TIJOLO | I2: =VLOOKUP(H2,$C:$F,4,FALSE) -> 0.35
C3: =D3&"-"&E3 -> Conservador-PAPEL | D3: Conservador | E3: PAPEL | F3: 0.3
C4: =D4&"-"&E4 -> Conservador-TIJOLO | D4: Conservador | E4: TIJOLO | F4: 0.5
C5: =D5&"-"&E5 -> Conservador-HÍBRIDOS | D5: Conservador | E5: HÍBRIDOS | F5: 0.1
C6: =D6&"-"&E6 -> Conservador-FOFs | D6: Conservador | E6: FOFs | F6: 0.1
C7: =D7&"-"&E7 -> Conservador-DESENVOLVIMENTO | D7: Conservador | E7: DESENVOLVIMENTO | F7: 0
C8: =D8&"-"&E8 -> Conservador-HOTELARIAS | D8: Conservador | E8: HOTELARIAS | F8: 0
C9: =D9&"-"&E9 -> Moderado-PAPEL | D9: Moderado | E9: PAPEL | F9: 0.32
C10: =D10&"-"&E10 -> Moderado-TIJOLO | D10: Moderado | E10: TIJOLO | F10: 0.35
C11: =D11&"-"&E11 -> Moderado-HÍBRIDOS | D11: Moderado | E11: HÍBRIDOS | F11: 0.08
C12: =D12&"-"&E12 -> Moderado-FOFs | D12: Moderado | E12: FOFs | F12: 0.05
C13: =D13&"-"&E13 -> Moderado-DESENVOLVIMENTO | D13: Moderado | E13: DESENVOLVIMENTO | F13: 0.1
C14: =D14&"-"&E14 -> Moderado-HOTELARIAS | D14: Moderado | E14: HOTELARIAS | F14: 0.1
... C20: =D20&"-"&E20 -> Agressivo-HOTELARIAS | D20: Agressivo | E20: HOTELARIAS | F20: 0.1
